qit/__init__.py
qit/base.py
qit/examples.py
qit/gate.py
qit/hamiltonian.py
qit/ho.py
qit/invariant.py
qit/lmap.py
qit/markov.py
qit/plot.py
qit/seq.py
qit/state.py
qit/utils.py
qit-0.12.0.dist-info/AUTHORS.rst
qit-0.12.0.dist-info/LICENSE.txt
qit-0.12.0.dist-info/METADATA
qit-0.12.0.dist-info/WHEEL
qit-0.12.0.dist-info/top_level.txt
qit-0.12.0.dist-info/RECORD
