Metadata-Version: 2.1
Name: qit
Version: 0.12.0
Summary: Quantum Information Toolkit
Home-page: http://qit.sourceforge.net/
Author: Ville Bergholm et al.
Author-email: smite-meister@users.sourceforge.net
License: GPLv3
Project-URL: Documentation, http://qit.sourceforge.net/docs/html/
Keywords: quantum information,quantum mechanics,toolkit
Platform: any
Classifier: Development Status :: 4 - Beta
Classifier: Intended Audience :: End Users/Desktop
Classifier: Intended Audience :: Science/Research
Classifier: Intended Audience :: Information Technology
Classifier: Topic :: Scientific/Engineering :: Physics
Classifier: License :: OSI Approved :: GNU General Public License v3 (GPLv3)
Classifier: Operating System :: OS Independent
Classifier: Programming Language :: Python :: 3 :: Only
Requires-Python: ~=3.9
Provides-Extra: dev
Provides-Extra: docs
License-File: LICENSE.txt
License-File: AUTHORS.rst
